dolomite_matrix/DelayedMask.py
dolomite_matrix/ReloadedArray.py
dolomite_matrix/WrapperArraySeed.py
dolomite_matrix/__init__.py
dolomite_matrix/_optimize_storage.py
dolomite_matrix/_utils.py
dolomite_matrix/choose_chunk_dimensions.py
dolomite_matrix/read_compressed_sparse_matrix.py
dolomite_matrix/read_dense_array.py
dolomite_matrix/save_compressed_sparse_matrix.py
dolomite_matrix/save_delayed_array.py
dolomite_matrix/save_dense_array.py
dolomite_matrix-0.4.1.dist-info/LICENSE.txt
dolomite_matrix-0.4.1.dist-info/METADATA
dolomite_matrix-0.4.1.dist-info/WHEEL
dolomite_matrix-0.4.1.dist-info/top_level.txt
dolomite_matrix-0.4.1.dist-info/RECORD
