Metadata-Version: 2.2
Name: dolomite-matrix
Version: 0.4.1
Summary: Save and load matrices in the dolomite framework
Home-page: https://github.com/ArtifactDB/dolomite-matrix
Author: LTLA
Author-email: infinite.monkeys.with.keyboards@gmail.com
License: MIT
Project-URL: Documentation, https://artifactdb.github.io/dolomite-matrix/
Platform: any
Classifier: Development Status :: 4 - Beta
Classifier: Programming Language :: Python
Requires-Python: >=3.9
License-File: LICENSE.txt
Requires-Dist: importlib-metadata; python_version < "3.8"
Requires-Dist: dolomite-base>=0.4.2
Requires-Dist: delayedarray>=0.5.0
Requires-Dist: h5py
Requires-Dist: numpy
Requires-Dist: hdf5array
Provides-Extra: testing
Requires-Dist: setuptools; extra == "testing"
Requires-Dist: pytest; extra == "testing"
Requires-Dist: pytest-cov; extra == "testing"
Requires-Dist: scipy; extra == "testing"
Requires-Dist: dask; extra == "testing"
